{
	"name": "dwc",
	"description": "A minimal D application.",
	"copyright": "Copyright © 2014, rikki",
	"authors": ["rikki"],
	"dependencies": {
	},
	"sourcePaths": [],
	"subPackages": [
		{
			"name": "interfaces",
			"sourcePaths": ["interfaces"],
			"importPaths": ["interfaces"]
		},
		{
			"name": "platform",
            "targetType": "sourceLibrary",
            
			"sourcePaths-windows": ["platforms/win32", "WindowsAPI"],
			"importPaths-windows": ["platforms/win32", "WindowsAPI"],
			"libs-windows": ["user32", "gdi32"],
			
			"sourcePaths-linux": ["platforms/linux"],
			"importPaths-linux": ["platforms/linux"],
			"libs-linux": ["Xrandr"],
			
			"dependencies-linux": {
				"x11": ">=1.0.0"
			},
			
			"sourcePaths-osx": ["platforms/macosx"],
			"importPaths-osx": ["platforms/macosx"],
			"lflags-osx": ["/System/Library/Frameworks/Cocoa.framework/Cocoa"],
			"sourceFiles-osx": ["cocoa_library/bin/Debug/libdwc-osx.a"],
			
			"dependencies": {
				"dwc:interfaces": "~master",
                "derelict-gl3": ">=1.0.4"
			}
		},
		{
			"name": "test",
			"sourcePaths": ["test"],
			"importPaths": ["test"],
			"targetType": "executable",
			"dependencies": {
				"dwc:platform": "~master"	
			}
		}
	]
}
